papai_unified_storage/__init__.py
papai_unified_storage/papai.py
papai_unified_storage/py.typed
papai_unified_storage/storage.py
papai_unified_storage/utils.py
papai_unified_storage-0.23.1.dist-info/METADATA
papai_unified_storage-0.23.1.dist-info/WHEEL
papai_unified_storage-0.23.1.dist-info/top_level.txt
papai_unified_storage-0.23.1.dist-info/RECORD
